<manifest alg="2" build="30" opt="true" iceEnabled="true">
  <folder name="css">
    <file name="site_global.css" crc="3871673238"/>
    <file name="master_a-master.css" crc="4195300114" ref="suits:clothiers:jackets:products:index:about-us:creatively-prof:contact-form:flippics:shirts:comfortably-casual:clothier-1:all-business:lookbook:our-process"/>
    <file name="master_b-master.css" crc="520662619" ref="slider"/>
    <file name="suits.css" crc="323881675" ref="suits"/>
    <file name="clothiers.css" crc="4060167976" ref="clothiers"/>
    <file name="iefonts_clothiers.css" crc="4100975015" ref="clothiers"/>
    <file name="jackets.css" crc="492572651" ref="jackets"/>
    <file name="products.css" crc="4236010370" ref="products"/>
    <file name="iefonts_products.css" crc="443149600" ref="products"/>
    <file name="slider.css" crc="394074589" ref="slider"/>
    <file name="index.css" crc="103220215" ref="index"/>
    <file name="iefonts_index.css" crc="4110938949" ref="index"/>
    <file name="about-us.css" crc="4247655940" ref="about-us"/>
    <file name="iefonts_about-us.css" crc="3902097337" ref="about-us"/>
    <file name="creatively-prof.css" crc="118659089" ref="creatively-prof"/>
    <file name="contact-form.css" crc="4091826731" ref="contact-form"/>
    <file name="iefonts_contact-form.css" crc="461743137" ref="contact-form"/>
    <file name="flippics.css" crc="3955950450" ref="flippics"/>
    <file name="iefonts_flippics.css" crc="177040764" ref="flippics"/>
    <file name="shirts.css" crc="208377358" ref="shirts"/>
    <file name="comfortably-casual.css" crc="3863480864" ref="comfortably-casual"/>
    <file name="clothier-1.css" crc="503228713" ref="clothier-1"/>
    <file name="iefonts_clothier-1.css" crc="4047338847" ref="clothier-1"/>
    <file name="all-business.css" crc="3875318" ref="all-business"/>
    <file name="lookbook.css" crc="3921680118" ref="lookbook"/>
    <file name="iefonts_lookbook.css" crc="3823781077" ref="lookbook"/>
    <file name="our-process.css" crc="440313659" ref="our-process"/>
    <file name="iefonts_our-process.css" crc="4141190535" ref="our-process"/>
  </folder>
  <folder name="assets">
    <file name="hanger.svg" crc="4047857649" mt="1396142384000"/>
    <file name="video.mp4" crc="3933911904" mt="1394653684000"/>
    <file name="video.webm" crc="4266387636" mt="1401868963000"/>
    <file name="small1812vid.mp4" crc="509920750" mt="1401867866000"/>
    <file name="small1812vid.webm" crc="4202579717" mt="1401870364000"/>
    <file name="video-pattern-two.png" crc="3802565248" mt="1384623892000"/>
    <file name="video-pattern.png" crc="337489013" mt="1390574142000"/>
  </folder>
  <folder name="scripts">
    <file name="jquery-1.8.3.min.js" crc="3828297711" ref="index:our-process:clothiers:products:contact-form:lookbook:suits:jackets:shirts:all-business:creatively-prof:comfortably-casual:clothier-1:slider:flippics:about-us"/>
    <file name="museutils.js" crc="3880880085" ref="index:our-process:clothiers:products:contact-form:lookbook:suits:jackets:shirts:all-business:creatively-prof:comfortably-casual:clothier-1:slider:flippics:about-us"/>
    <file name="jquery.tobrowserwidth.js" crc="152985095" ref="index:our-process:clothiers:products:contact-form:lookbook:suits:jackets:shirts:all-business:creatively-prof:comfortably-casual:clothier-1:flippics:about-us"/>
    <file name="jquery.musepolyfill.bgsize.js" crc="3899542795" ref="index:our-process:clothiers:products:contact-form:lookbook:suits:jackets:shirts:clothier-1:flippics:about-us"/>
    <file name="jquery.scrolleffects.js" crc="56249048" ref="index:our-process"/>
    <file name="pie.js" crc="4147615982" ref="index:our-process:clothiers:products:contact-form:lookbook:clothier-1:slider:flippics:about-us"/>
    <file name="webpro.js" crc="33264525" ref="index:our-process:clothiers:products:contact-form:lookbook:suits:jackets:shirts:all-business:creatively-prof:comfortably-casual:clothier-1:slider:flippics:about-us"/>
    <file name="musewpslideshow.js" crc="272207905" ref="index:our-process:clothiers:products:contact-form:lookbook:suits:jackets:shirts:all-business:creatively-prof:comfortably-casual:clothier-1:slider:flippics:about-us"/>
    <file name="jquery.museoverlay.js" crc="466079611" ref="index:our-process:clothiers:products:contact-form:lookbook:suits:jackets:shirts:all-business:creatively-prof:comfortably-casual:clothier-1:slider:flippics:about-us"/>
    <file name="touchswipe.js" crc="261777990" ref="index:our-process:clothiers:products:contact-form:lookbook:suits:jackets:shirts:all-business:creatively-prof:comfortably-casual:clothier-1:slider:flippics:about-us"/>
  </folder>
  <folder name="images">
    <file name="290a5045_8blue.jpg" crc="333213481" ref="index"/>
    <file name="1812_society_logo_onwhitetrans_revised.png" crc="4101510563" ref="index"/>
    <file name="mediaicon-u5857-fr.png" crc="4105565733" ref="index"/>
    <file name="mediaicon.png" crc="170921153" ref="index"/>
    <file name="hanger200x200.png" crc="303168252" ref="index"/>
    <file name="u2390-4.png" crc="294465228" ref="index:our-process:clothiers:products:contact-form:lookbook:suits:jackets:shirts:all-business:creatively-prof:comfortably-casual:clothier-1:flippics:about-us"/>
    <file name="final1654_800.jpg" crc="3895461329" ref="index:lookbook"/>
    <file name="finalbryce0987_800.jpg" crc="70437728" ref="index"/>
    <file name="finalmatt_0298_800.jpg" crc="281523659" ref="index"/>
    <file name="hanger180x180.png" crc="292959640" ref="index"/>
    <file name="logo1812.png" crc="132570861" ref="index"/>
    <file name="mediaicon-u6388-fr.png" crc="3857324245" ref="index"/>
    <file name="blank.gif" crc="4208392903" ref="index:our-process:clothiers:products:contact-form:lookbook:suits:jackets:shirts:all-business:creatively-prof:comfortably-casual:clothier-1:slider:flippics:about-us"/>
    <file name="u813_states.png" crc="4137910115" ref="index:our-process:clothiers:products:contact-form:lookbook:suits:jackets:shirts:all-business:creatively-prof:comfortably-casual:clothier-1:flippics:about-us"/>
    <file name="u813_states-r.png" crc="4183173870" ref="index:our-process:clothiers:products:contact-form:lookbook:suits:jackets:shirts:all-business:creatively-prof:comfortably-casual:clothier-1:flippics:about-us"/>
    <file name="u813_states-a.png" crc="440868639" ref="index:our-process:clothiers:products:contact-form:lookbook:suits:jackets:shirts:all-business:creatively-prof:comfortably-casual:clothier-1:flippics:about-us"/>
    <file name="u814_states.png" crc="3839581359" ref="index:our-process:clothiers:products:contact-form:lookbook:suits:jackets:shirts:all-business:creatively-prof:comfortably-casual:clothier-1:flippics:about-us"/>
    <file name="u814_states-r.png" crc="3896783971" ref="index:our-process:clothiers:products:contact-form:lookbook:suits:jackets:shirts:all-business:creatively-prof:comfortably-casual:clothier-1:flippics:about-us"/>
    <file name="u814_states-a.png" crc="4103099204" ref="index:our-process:clothiers:products:contact-form:lookbook:suits:jackets:shirts:all-business:creatively-prof:comfortably-casual:clothier-1:flippics:about-us"/>
    <file name="u815_states.png" crc="152401793" ref="index:our-process:clothiers:products:contact-form:lookbook:suits:jackets:shirts:all-business:creatively-prof:comfortably-casual:clothier-1:flippics:about-us"/>
    <file name="u815_states-r.png" crc="3876063641" ref="index:our-process:clothiers:products:contact-form:lookbook:suits:jackets:shirts:all-business:creatively-prof:comfortably-casual:clothier-1:flippics:about-us"/>
    <file name="u815_states-a.png" crc="4168657092" ref="index:our-process:clothiers:products:contact-form:lookbook:suits:jackets:shirts:all-business:creatively-prof:comfortably-casual:clothier-1:flippics:about-us"/>
    <file name="u816_states.png" crc="389628964" ref="index:our-process:clothiers:products:contact-form:lookbook:suits:jackets:shirts:all-business:creatively-prof:comfortably-casual:clothier-1:flippics:about-us"/>
    <file name="u816_states-r.png" crc="4169113724" ref="index:our-process:clothiers:products:contact-form:lookbook:suits:jackets:shirts:all-business:creatively-prof:comfortably-casual:clothier-1:flippics:about-us"/>
    <file name="u816_states-a.png" crc="74862267" ref="index:our-process:clothiers:products:contact-form:lookbook:suits:jackets:shirts:all-business:creatively-prof:comfortably-casual:clothier-1:flippics:about-us"/>
    <file name="u817_states.png" crc="508448202" ref="index:our-process:clothiers:products:contact-form:lookbook:suits:jackets:shirts:all-business:creatively-prof:comfortably-casual:clothier-1:flippics:about-us"/>
    <file name="u817_states-r.png" crc="272691407" ref="index:our-process:clothiers:products:contact-form:lookbook:suits:jackets:shirts:all-business:creatively-prof:comfortably-casual:clothier-1:flippics:about-us"/>
    <file name="u817_states-a.png" crc="3938306317" ref="index:our-process:clothiers:products:contact-form:lookbook:suits:jackets:shirts:all-business:creatively-prof:comfortably-casual:clothier-1:flippics:about-us"/>
    <file name="u818_states.png" crc="315191834" ref="index:our-process:clothiers:products:contact-form:lookbook:suits:jackets:shirts:all-business:creatively-prof:comfortably-casual:clothier-1:flippics:about-us"/>
    <file name="u818_states-r.png" crc="4236895006" ref="index:our-process:clothiers:products:contact-form:lookbook:suits:jackets:shirts:all-business:creatively-prof:comfortably-casual:clothier-1:flippics:about-us"/>
    <file name="u818_states-a.png" crc="381514434" ref="index:our-process:clothiers:products:contact-form:lookbook:suits:jackets:shirts:all-business:creatively-prof:comfortably-casual:clothier-1:flippics:about-us"/>
    <file name="290a4930_3-u396-fr.jpg" crc="304881846" ref="index"/>
    <file name="img_7284_25-u388-fr.jpg" crc="4127927149" ref="index"/>
    <file name="img_7284_25-u388-r-fr.png" crc="342265958" ref="index"/>
    <file name="jacketsbw-u2853-fr.jpg" crc="3771044002" ref="index"/>
    <file name="img_4856_26-u2854-fr.jpg" crc="12418763" ref="index"/>
    <file name="final8570-u2854-r-fr.jpg" crc="4161322993" ref="index"/>
    <file name="img_7284-u4321-fr.jpg" crc="436371140" ref="index"/>
    <file name="u2891_states.png" crc="511315489" ref="index"/>
    <file name="u2891_states-r.png" crc="4116248214" ref="index"/>
    <file name="img_4856-u4481-fr.jpg" crc="3971560039" ref="index"/>
    <file name="u2894_states.png" crc="293081638" ref="index"/>
    <file name="u2894_states-r.png" crc="454015913" ref="index"/>
    <file name="290a8221_19-u4527-fr.jpg" crc="3784517493" ref="index"/>
    <file name="290a8221_19-u4527-r-fr.png" crc="107997529" ref="index"/>
    <file name="290a8221-u5755-fr.jpg" crc="3791444872" ref="index"/>
    <file name="u2895_states.png" crc="4094949025" ref="index"/>
    <file name="u2895_states-r.png" crc="3853836023" ref="index"/>
    <file name="290a4930-u5815-fr.jpg" crc="3800603980" ref="index"/>
    <file name="u5846_states.png" crc="116778350" ref="index"/>
    <file name="u5846_states-r.png" crc="371420688" ref="index"/>
    <file name="jackets-u6724-fr.jpg" crc="215704278" ref="index"/>
    <file name="u2893_states.png" crc="3933656983" ref="index"/>
    <file name="u2893_states-r.png" crc="3879101173" ref="index"/>
    <file name="schedule180x180.png" crc="3759909127" ref="index"/>
    <file name="u2026-6.png" crc="34634538" ref="index:our-process:clothiers:products:contact-form:lookbook:suits:jackets:shirts:all-business:creatively-prof:comfortably-casual:clothier-1:flippics:about-us"/>
    <file name="facebook.png" crc="4061617475" ref="index:clothier-1"/>
    <file name="facebook-u2029-r-fr.png" crc="4041710746" ref="index"/>
    <file name="twitter.png" crc="311493227" ref="index:clothier-1"/>
    <file name="twitter-u2031-r-fr.png" crc="3776536129" ref="index"/>
    <file name="instagram.png" crc="228408437" ref="index:clothier-1"/>
    <file name="instagram-u2030-r-fr.png" crc="4166975004" ref="index"/>
    <file name="wave2.jpg" crc="3887357415" ref="index"/>
    <file name="1812_society_logo_onblacktrans_revised.png" crc="95140989" ref="index"/>
    <file name="u2896_states.png" crc="3963296734" ref="index"/>
    <file name="u2896_states-r.png" crc="125966069" ref="index"/>
    <file name="img_4856_26.jpg" crc="336575230" ref="our-process"/>
    <file name="u2902-4.png" crc="3923387025" ref="our-process"/>
    <file name="scissors-u5491-fr.png" crc="3804388314" ref="our-process"/>
    <file name="290a4992.jpg" crc="4090759391" ref="our-process"/>
    <file name="u4579-4.png" crc="3950263060" ref="our-process"/>
    <file name="meet-u5425-fr.png" crc="4162443145" ref="our-process"/>
    <file name="290a4939.jpg" crc="3966396510" ref="our-process"/>
    <file name="measurewht-u5432-fr.png" crc="309214392" ref="our-process"/>
    <file name="u4586-4.png" crc="525863414" ref="our-process"/>
    <file name="scissorswt-u5893-fr.png" crc="476464681" ref="our-process"/>
    <file name="290a5080edit-u1088-fr.jpg" crc="4271146263" ref="our-process"/>
    <file name="u4590-4.png" crc="376687112" ref="our-process"/>
    <file name="designwht-u5457-fr.png" crc="516574564" ref="our-process"/>
    <file name="290a5275book.jpg" crc="451979321" ref="our-process"/>
    <file name="u4600-4.png" crc="168116582" ref="our-process"/>
    <file name="construct-u5464-fr.png" crc="117587299" ref="our-process"/>
    <file name="290a4892edit-u1090-fr.jpg" crc="474090381" ref="our-process"/>
    <file name="fittingwht-u5471-fr.png" crc="338071289" ref="our-process"/>
    <file name="u4606-4.png" crc="275009075" ref="our-process"/>
    <file name="img_4742.jpg" crc="108341840" ref="our-process"/>
    <file name="u4619-4.png" crc="310550618" ref="our-process"/>
    <file name="schedulewht-u5484-fr.png" crc="4255893564" ref="our-process"/>
    <file name="contact1.png" crc="248162083" ref="our-process"/>
    <file name="contact2.png" crc="495611515" ref="our-process"/>
    <file name="u4561_states.png" crc="3963296734" ref="our-process"/>
    <file name="u4561_states-r.png" crc="125966069" ref="our-process"/>
    <file name="290a5131.jpg" crc="524206943" ref="clothiers"/>
    <file name="290a5080.jpg" crc="444152134" ref="clothiers"/>
    <file name="u2900-4.png" crc="3974916725" ref="clothiers"/>
    <file name="patrickedit.jpg" crc="4254336" ref="clothiers:clothier-1"/>
    <file name="patrickedit-u1910-r-fr.png" crc="505045927" ref="clothiers"/>
    <file name="productsfade.jpg" crc="80465809" ref="products"/>
    <file name="u2903-4.png" crc="3981859546" ref="products"/>
    <file name="img_1827edit_800-u5669-fr.jpg" crc="91151082" ref="products"/>
    <file name="img_1820_800-u5655-fr.jpg" crc="4025180310" ref="products"/>
    <file name="canvassed-u6915-fr.jpg" crc="3860416838" ref="products"/>
    <file name="linings-u6933-fr.jpg" crc="363610288" ref="products"/>
    <file name="wholesuit-u6946-fr.jpg" crc="4119472276" ref="products"/>
    <file name="img_1834edit_800-u5700-fr.jpg" crc="70346607" ref="products"/>
    <file name="img_1863edit_800-u5562-fr.jpg" crc="79775417" ref="products"/>
    <file name="loopedit.jpg" crc="3801004496" ref="products"/>
    <file name="collar-u6886-fr.jpg" crc="399534857" ref="products"/>
    <file name="contact-u2119-fr.png" crc="4235144058" ref="contact-form"/>
    <file name="u2905-4.png" crc="4196510045" ref="contact-form"/>
    <file name="final1654_800-u5693-fr.jpg" crc="4284699123" ref="contact-form:suits"/>
    <file name="finalryan0884_800-u5691-fr.jpg" crc="4065606521" ref="contact-form:suits"/>
    <file name="finalsed2571_800-u5692-fr.jpg" crc="79962079" ref="contact-form"/>
    <file name="lookbookback-u6793-fr.png" crc="3365591" ref="lookbook"/>
    <file name="u3300-4.png" crc="366207419" ref="lookbook"/>
    <file name="finalsed2571_800-u3075-fr.jpg" crc="3836287414" ref="lookbook"/>
    <file name="finalsed2571_800-u3075-r-fr.png" crc="297509805" ref="lookbook"/>
    <file name="final1654_800-u3076-r-fr.png" crc="438241101" ref="lookbook"/>
    <file name="finaljoshua1126_800.jpg" crc="4278740488" ref="lookbook"/>
    <file name="finaljoshua1126_800-u3077-r-fr.png" crc="139883688" ref="lookbook"/>
    <file name="u3078_states.png" crc="106045919" ref="lookbook"/>
    <file name="u3078_states-r.png" crc="4239457146" ref="lookbook"/>
    <file name="u3079_states.png" crc="220189742" ref="lookbook"/>
    <file name="u3079_states-r.png" crc="354825603" ref="lookbook"/>
    <file name="u3080_states.png" crc="3967976574" ref="lookbook"/>
    <file name="u3080_states-r.png" crc="487019944" ref="lookbook"/>
    <file name="suits.png" crc="303257488" ref="suits"/>
    <file name="jackets-u2644-fr.png" crc="366544221" ref="suits"/>
    <file name="shirts-u2645-fr.png" crc="4187263285" ref="suits:jackets"/>
    <file name="finalbryce0987_800-u5574-fr.jpg" crc="4174620898" ref="suits"/>
    <file name="finalbryce1035_800-u5574-r-fr.jpg" crc="397412387" ref="suits:shirts"/>
    <file name="finalmatt_0298_800-u5576-fr.jpg" crc="139911353" ref="suits"/>
    <file name="finalryan0953_800-u5579-r-fr.jpg" crc="450859789" ref="suits:shirts"/>
    <file name="finalbryce1572_800-u5577-fr.jpg" crc="4023540950" ref="suits"/>
    <file name="finalbryce1614_800-u5577-r-fr.jpg" crc="4095406320" ref="suits:shirts"/>
    <file name="finalryan1255_800-u5578-fr.jpg" crc="4116130981" ref="suits"/>
    <file name="finaljoshua1162_800-u5925-fr.jpg" crc="3876264536" ref="suits"/>
    <file name="finajoshua1231_800-u5925-r-fr.jpg" crc="409986295" ref="suits:shirts"/>
    <file name="finalmatt_0318_800-u5923-fr.jpg" crc="223258137" ref="suits"/>
    <file name="finalmatt0397_800-u5923-r-fr.jpg" crc="233818304" ref="suits:shirts"/>
    <file name="finalryan1066_800-u5924-fr.jpg" crc="3866766543" ref="suits"/>
    <file name="finalryan1101_800-u5924-r-fr.jpg" crc="4156689871" ref="suits:shirts"/>
    <file name="finalbryce1992_800-u5922-fr.jpg" crc="4286011541" ref="suits"/>
    <file name="finalbryce2022_800-u5922-r-fr.jpg" crc="3855611846" ref="suits:shirts"/>
    <file name="finalmatt0458_800-u5920-fr.jpg" crc="320088526" ref="suits"/>
    <file name="finalmatt0479_800-u5920-r-fr.jpg" crc="3967182474" ref="suits"/>
    <file name="finalbryce2758_800-u5921-fr.jpg" crc="3988501658" ref="suits"/>
    <file name="finalbryce2802_800-u5921-r-fr.jpg" crc="218259733" ref="suits:shirts"/>
    <file name="jackets.png" crc="4062272290" ref="jackets"/>
    <file name="suits-u2652-fr.png" crc="4020699773" ref="jackets:shirts"/>
    <file name="final1729_800-u6526-fr.jpg" crc="488288191" ref="jackets"/>
    <file name="final2063_800-u6524-fr.jpg" crc="299876133" ref="jackets"/>
    <file name="finaljoshua2116_800-u6524-r-fr.jpg" crc="3903313065" ref="jackets"/>
    <file name="finalbryce2360_800-u6525-fr.jpg" crc="4234163841" ref="jackets"/>
    <file name="finalbryce2407_800-u6525-r-fr.jpg" crc="4010093616" ref="jackets"/>
    <file name="finalbryce2229_800-u6523-fr.jpg" crc="3821055080" ref="jackets"/>
    <file name="finalbryce2247_800-u6523-r-fr.jpg" crc="110939371" ref="jackets"/>
    <file name="final2696_800-u6521-fr.jpg" crc="315092217" ref="jackets"/>
    <file name="finaljoshua2737_800-u6521-r-fr.jpg" crc="4001527202" ref="jackets"/>
    <file name="finalbryce2528_800-u6522-fr.jpg" crc="220681555" ref="jackets"/>
    <file name="finalbryce2536_800-u6522-r-fr.jpg" crc="450625552" ref="jackets"/>
    <file name="finalmatt0499_800-u6532-fr.jpg" crc="3828286883" ref="jackets"/>
    <file name="finalmatt0576_800-u6532-r-fr.jpg" crc="440017203" ref="jackets"/>
    <file name="finaljoshua2259_800-u6530-fr.jpg" crc="4041876639" ref="jackets"/>
    <file name="finaljoshua2340_800-u6530-r-fr.jpg" crc="4064744266" ref="jackets"/>
    <file name="finalmatt0731_800-u6531-fr.jpg" crc="49239035" ref="jackets"/>
    <file name="finalmatt0791_800-u6531-r-fr.jpg" crc="160666143" ref="jackets"/>
    <file name="finalryan1504_800-u6529-fr.jpg" crc="4007818863" ref="jackets"/>
    <file name="finalryan1551_800-u6529-r-fr.jpg" crc="4278118025" ref="jackets"/>
    <file name="finalryan1912_800-u6527-fr.jpg" crc="3778009079" ref="jackets"/>
    <file name="finalmatt0631_800-u6528-fr.jpg" crc="367410460" ref="jackets"/>
    <file name="finalmatt0684_800-u6528-r-fr.jpg" crc="345889631" ref="jackets"/>
    <file name="shirts.png" crc="3916245711" ref="shirts"/>
    <file name="jackets-u2661-fr.png" crc="366544221" ref="shirts"/>
    <file name="finalmatt0466_800-u6509-r-fr.jpg" crc="279850457" ref="shirts"/>
    <file name="u2906-4.png" crc="3885832153" ref="all-business"/>
    <file name="01.jpg" crc="479007123" ref="all-business:creatively-prof:comfortably-casual"/>
    <file name="02.jpg" crc="4195038050" ref="all-business:creatively-prof:comfortably-casual"/>
    <file name="35.jpg" crc="3759393954" ref="all-business:creatively-prof:comfortably-casual"/>
    <file name="03.jpg" crc="30434855" ref="all-business:creatively-prof:comfortably-casual"/>
    <file name="u3211-4.png" crc="3885832153" ref="creatively-prof"/>
    <file name="u3243-4.png" crc="3885832153" ref="comfortably-casual"/>
    <file name="u2844-4.png" crc="341983872" ref="clothier-1"/>
    <file name="facebook-u2845-r-fr.png" crc="3983307222" ref="clothier-1"/>
    <file name="instagram-u2846-r-fr.png" crc="420987567" ref="clothier-1"/>
    <file name="twitter-u2847-r-fr.png" crc="256636328" ref="clothier-1"/>
    <file name="1final5236.jpg" crc="222311247" ref="slider"/>
    <file name="290a5252.jpg" crc="3844252756" ref="slider"/>
    <file name="290a5533.jpg" crc="4157165439" ref="slider"/>
    <file name="290a5633.jpg" crc="208504613" ref="slider"/>
    <file name="final8528city2.jpg" crc="64963225" ref="slider"/>
    <file name="290a5662.jpg" crc="4035868926" ref="slider"/>
    <file name="290a8160.jpg" crc="4144411026" ref="slider"/>
    <file name="final8570.jpg" crc="21958576" ref="slider"/>
    <file name="img_5253.jpg" crc="265146008" ref="slider"/>
    <file name="loading.gif" crc="3815509949" ref="slider:flippics"/>
    <file name="290a5095_11dark.jpg" crc="4195589718" ref="flippics"/>
    <file name="1final4647_800.jpg" crc="3893549743" ref="flippics"/>
    <file name="1final4783_800.jpg" crc="4294515333" ref="flippics"/>
    <file name="1final5236_800.jpg" crc="4151190266" ref="flippics"/>
    <file name="1final5459_800.jpg" crc="488050558" ref="flippics"/>
    <file name="1final6388_800.jpg" crc="3913235869" ref="flippics"/>
    <file name="bigcollage1812_800.jpg" crc="4100795620" ref="flippics"/>
    <file name="collage1812_800.jpg" crc="3992610979" ref="flippics"/>
    <file name="final_8401hicsky_800.jpg" crc="287463708" ref="flippics"/>
    <file name="final_8460_800.jpg" crc="419724504" ref="flippics"/>
    <file name="final290a5767_800.jpg" crc="90097526" ref="flippics"/>
    <file name="final4267_800.jpg" crc="469178481" ref="flippics"/>
    <file name="final4308_800.jpg" crc="3889848769" ref="flippics"/>
    <file name="final4540_800.jpg" crc="3913839712" ref="flippics"/>
    <file name="final4590_800.jpg" crc="4022006370" ref="flippics"/>
    <file name="final4887_800.jpg" crc="397355975" ref="flippics"/>
    <file name="final6817_800.jpg" crc="29759207" ref="flippics"/>
    <file name="final7456_800.jpg" crc="160760159" ref="flippics"/>
    <file name="final7560_800.jpg" crc="4283807119" ref="flippics"/>
    <file name="final7606_800.jpg" crc="307949173" ref="flippics"/>
    <file name="final7932_800.jpg" crc="100113110" ref="flippics"/>
    <file name="final8273copy_800.jpg" crc="295013270" ref="flippics"/>
    <file name="final8570_800.jpg" crc="37936104" ref="flippics"/>
    <file name="finaledit4711_800.jpg" crc="4137194302" ref="flippics"/>
    <file name="finaledit4887_800.jpg" crc="96774511" ref="flippics"/>
    <file name="img_8071-recovered2_800.jpg" crc="4139279399" ref="flippics"/>
    <file name="img_7284.jpg" crc="422451727" ref="about-us"/>
    <file name="u5412-4.png" crc="4043684038" ref="about-us"/>
    <file name="u5411-49.png" crc="440602260" ref="about-us"/>
  </folder>
  <file name="index.html" crc="21586078" mt="1403289519939" redirect="true"/>
  <file name="our-process.html" crc="159464627" mt="1403125164380" redirect="true"/>
  <file name="clothiers.html" crc="3943197429" mt="1403124967176" redirect="true"/>
  <file name="products.html" crc="500530610" mt="1403289147126" redirect="true"/>
  <file name="contact-form.html" crc="58764666" mt="1403124967180" redirect="true"/>
  <file name="lookbook.html" crc="4258768849" mt="1403124967181" redirect="true"/>
  <file name="suits.html" crc="4042346715" mt="1403131464312" redirect="true"/>
  <file name="jackets.html" crc="299682742" mt="1403131455937" redirect="true"/>
  <file name="shirts.html" crc="38966617" mt="1403131440405" redirect="true"/>
  <file name="all-business.html" crc="418169300" mt="1403126333118" redirect="true"/>
  <file name="creatively-prof.html" crc="3968854471" mt="1403126326238" redirect="true"/>
  <file name="comfortably-casual.html" crc="197281643" mt="1403126319000" redirect="true"/>
  <file name="clothier-1.html" crc="168145484" mt="1403124967193" redirect="true"/>
  <file name="slider.html" crc="141154971" mt="1403285099411" redirect="true"/>
  <file name="flippics.html" crc="4235628547" mt="1403289421407" redirect="true"/>
  <file name="about-us.html" crc="236482457" mt="1403289469934" redirect="true"/>
</manifest>